Workbook

Sheet Metrics Dashboard
B2: Merchant Cash Advance — Metrics Dashboard
B4: Total Origination Principal by Partner & Month
B5: Formula-driven cross-tab (SUMIFS) of ORIGINATIONS!advance_amount_usd, grouped by partner_id and funding_month.
B7: Month | C7: DoorDash | D7: Amazon | E7: Worldpay | F7: Mindbody | G7: Toast | H7: Squarespace | I7: Total
B8: 2022-01 | C8: =SUMIFS(ORIGINATIONS!$L:$L,ORIGINATIONS!$C:$C,"PTR-001",ORIGINATIONS!$U:$U,$B8) -> 182124.15 | D8: =SUMIFS(ORIGINATIONS!$L:$L,ORIGINATIONS!$C:$C,"PTR-002",ORIGINATIONS!$U:$U,$B8) -> 161103.56 | E8: =SUMIFS(ORIGINATIONS!$L:$L,ORIGINATIONS!$C:$C,"PTR-003",ORIGINATIONS!$U:$U,$B8) -> 122796.57 | F8: =SUMIFS(ORIGINATIONS!$L:$L,ORIGINATIONS!$C:$C,"PTR-004",ORIGINATIONS!$U:$U,$B8) -> 89897.78 | G8: =SUMIFS(ORIGINATIONS!$L:$L,ORIGINATIONS!$C:$C,"PTR-005",ORIGINATIONS!$U:$U,$B8) -> 275724.6 | H8: =SUMIFS(ORIGINATIONS!$L:$L,ORIGINATIONS!$C:$C,"PTR-006",ORIGINATIONS!$U:$U,$B8) -> 185785.99 | I8: =SUM(C8:H8) -> 1017432.7
B9: 2022-02 | C9: =SUMIFS(ORIGINATIONS!$L:$L,ORIGINATIONS!$C:$C,"PTR-001",ORIGINATIONS!$U:$U,$B9) -> 105545.23 | D9: =SUMIFS(ORIGINATIONS!$L:$L,ORIGINATIONS!$C:$C,"PTR-002",ORIGINATIONS!$U:$U,$B9) -> 20450.72 | E9: =SUMIFS(ORIGINATIONS!$L:$L,ORIGINATIONS!$C:$C,"PTR-003",ORIGINATIONS!$U:$U,$B9) -> 111538.65 | F9: =SUMIFS(ORIGINATIONS!$L:$L,ORIGINATIONS!$C:$C,"PTR-004",ORIGINATIONS!$U:$U,$B9) -> 37121.91 | G9: =SUMIFS(ORIGINATIONS!$L:$L,ORIGINATIONS!$C:$C,"PTR-005",ORIGINATIONS!$U:$U,$B9) -> 29767.2 | H9: =SUMIFS(ORIGINATIONS!$L:$L,ORIGINATIONS!$C:$C,"PTR-006",ORIGINATIONS!$U:$U,$B9) -> 227436.64 | I9: =SUM(C9:H9) -> 531860.35
B10: 2022-03 | C10: =SUMIFS(ORIGINATIONS!$L:$L,ORIGINATIONS!$C:$C,"PTR-001",ORIGINATIONS!$U:$U,$B10) -> 82822.11 | D10: =SUMIFS(ORIGINATIONS!$L:$L,ORIGINATIONS!$C:$C,"PTR-002",ORIGINATIONS!$U:$U,$B10) -> 177558.93 | E10: =SUMIFS(ORIGINATIONS!$L:$L,ORIGINATIONS!$C:$C,"PTR-003",ORIGINATIONS!$U:$U,$B10) -> 115737.94 | F10: =SUMIFS(ORIGINATIONS!$L:$L,ORIGINATIONS!$C:$C,"PTR-004",ORIGINATIONS!$U:$U,$B10) -> 117260.18 | G10: =SUMIFS(ORIGINATIONS!$L:$L,ORIGINATIONS!$C:$C,"PTR-005",ORIGINATIONS!$U:$U,$B10) -> 104008.23 | H10: =SUMIFS(ORIGINATIONS!$L:$L,ORIGINATIONS!$C:$C,"PTR-006",ORIGINATIONS!$U:$U,$B10) -> 146810.89 | I10: =SUM(C10:H10) -> 744198.28
B11: 2022-04 | C11: =SUMIFS(ORIGINATIONS!$L:$L,ORIGINATIONS!$C:$C,"PTR-001",ORIGINATIONS!$U:$U,$B11) -> 264578.4 | D11: =SUMIFS(ORIGINATIONS!$L:$L,ORIGINATIONS!$C:$C,"PTR-002",ORIGINATIONS!$U:$U,$B11) -> 190174.42 | E11: =SUMIFS(ORIGINATIONS!$L:$L,ORIGINATIONS!$C:$C,"PTR-003",ORIGINATIONS!$U:$U,$B11) -> 216047.69 | F11: =SUMIFS(ORIGINATIONS!$L:$L,ORIGINATIONS!$C:$C,"PTR-004",ORIGINATIONS!$U:$U,$B11) -> 68693.98 | G11: =SUMIFS(ORIGINATIONS!$L:$L,ORIGINATIONS!$C:$C,"PTR-005",ORIGINATIONS!$U:$U,$B11) -> 66031.42 | H11: =SUMIFS(ORIGINATIONS!$L:$L,ORIGINATIONS!$C:$C,"PTR-006",ORIGINATIONS!$U:$U,$B11) -> 208159.5 | I11: =SUM(C11:H11) -> 1013685.4
B12: 2022-05 | C12: =SUMIFS(ORIGINATIONS!$L:$L,ORIGINATIONS!$C:$C,"PTR-001",ORIGINATIONS!$U:$U,$B12) -> 229755.63 | D12: =SUMIFS(ORIGINATIONS!$L:$L,ORIGINATIONS!$C:$C,"PTR-002",ORIGINATIONS!$U:$U,$B12) -> 0 | E12: =SUMIFS(ORIGINATIONS!$L:$L,ORIGINATIONS!$C:$C,"PTR-003",ORIGINATIONS!$U:$U,$B12) -> 2372.66 | F12: =SUMIFS(ORIGINATIONS!$L:$L,ORIGINATIONS!$C:$C,"PTR-004",ORIGINATIONS!$U:$U,$B12) -> 94742.77 | G12: =SUMIFS(ORIGINATIONS!$L:$L,ORIGINATIONS!$C:$C,"PTR-005",ORIGINATIONS!$U:$U,$B12) -> 53486.51 | H12: =SUMIFS(ORIGINATIONS!$L:$L,ORIGINATIONS!$C:$C,"PTR-006",ORIGINATIONS!$U:$U,$B12) -> 268698.36 | I12: =SUM(C12:H12) -> 649055.93
B13: 2022-06 | C13: =SUMIFS(ORIGINATIONS!$L:$L,ORIGINATIONS!$C:$C,"PTR-001",ORIGINATIONS!$U:$U,$B13) -> 403052.75 | D13: =SUMIFS(ORIGINATIONS!$L:$L,ORIGINATIONS!$C:$C,"PTR-002",ORIGINATIONS!$U:$U,$B13) -> 163801.83 | E13: =SUMIFS(ORIGINATIONS!$L:$L,ORIGINATIONS!$C:$C,"PTR-003",ORIGINATIONS!$U:$U,$B13) -> 99277.09 | F13: =SUMIFS(ORIGINATIONS!$L:$L,ORIGINATIONS!$C:$C,"PTR-004",ORIGINATIONS!$U:$U,$B13) -> 18389.99 | G13: =SUMIFS(ORIGINATIONS!$L:$L,ORIGINATIONS!$C:$C,"PTR-005",ORIGINATIONS!$U:$U,$B13) -> 48977.53 | H13: =SUMIFS(ORIGINATIONS!$L:$L,ORIGINATIONS!$C:$C,"PTR-006",ORIGINATIONS!$U:$U,$B13) -> 176834.21 | I13: =SUM(C13:H13) -> 910333.4
B14: 2022-07 | C14: =SUMIFS(ORIGINATIONS!$L:$L,ORIGINATIONS!$C:$C,"PTR-001",ORIGINATIONS!$U:$U,$B14) -> 61803.03 | D14: =SUMIFS(ORIGINATIONS!$L:$L,ORIGINATIONS!$C:$C,"PTR-002",ORIGINATIONS!$U:$U,$B14) -> 183044.9 | E14: =SUMIFS(ORIGINATIONS!$L:$L,ORIGINATIONS!$C:$C,"PTR-003",ORIGINATIONS!$U:$U,$B14) -> 156118.66 | F14: =SUMIFS(ORIGINATIONS!$L:$L,ORIGINATIONS!$C:$C,"PTR-004",ORIGINATIONS!$U:$U,$B14) -> 98706.8 | G14: =SUMIFS(ORIGINATIONS!$L:$L,ORIGINATIONS!$C:$C,"PTR-005",ORIGINATIONS!$U:$U,$B14) -> 226219.95 | H14: =SUMIFS(ORIGINATIONS!$L:$L,ORIGINATIONS!$C:$C,"PTR-006",ORIGINATIONS!$U:$U,$B14) -> 44092.45 | I14: =SUM(C14:H14) -> 769985.79
B15: 2022-08 | C15: =SUMIFS(ORIGINATIONS!$L:$L,ORIGINATIONS!$C:$C,"PTR-001",ORIGINATIONS!$U:$U,$B15) -> 38712.76 | D15: =SUMIFS(ORIGINATIONS!$L:$L,ORIGINATIONS!$C:$C,"PTR-002",ORIGINATIONS!$U:$U,$B15) -> 128859.73 | E15: =SUMIFS(ORIGINATIONS!$L:$L,ORIGINATIONS!$C:$C,"PTR-003",ORIGINATIONS!$U:$U,$B15) -> 139232.17 | F15: =SUMIFS(ORIGINATIONS!$L:$L,ORIGINATIONS!$C:$C,"PTR-004",ORIGINATIONS!$U:$U,$B15) -> 145079.88 | G15: =SUMIFS(ORIGINATIONS!$L:$L,ORIGINATIONS!$C:$C,"PTR-005",ORIGINATIONS!$U:$U,$B15) -> 104060.76 | H15: =SUMIFS(ORIGINATIONS!$L:$L,ORIGINATIONS!$C:$C,"PTR-006",ORIGINATIONS!$U:$U,$B15) -> 85149.51 | I15: =SUM(C15:H15) -> 641094.81
B16: 2022-09 | C16: =SUMIFS(ORIGINATIONS!$L:$L,ORIGINATIONS!$C:$C,"PTR-001",ORIGINATIONS!$U:$U,$B16) -> 221066.31 | D16: =SUMIFS(ORIGINATIONS!$L:$L,ORIGINATIONS!$C:$C,"PTR-002",ORIGINATIONS!$U:$U,$B16) -> 205361.36 | E16: =SUMIFS(ORIGINATIONS!$L:$L,ORIGINATIONS!$C:$C,"PTR-003",ORIGINATIONS!$U:$U,$B16) -> 25144.12 | F16: =SUMIFS(ORIGINATIONS!$L:$L,ORIGINATIONS!$C:$C,"PTR-004",ORIGINATIONS!$U:$U,$B16) -> 233785.94 | G16: =SUMIFS(ORIGINATIONS!$L:$L,ORIGINATIONS!$C:$C,"PTR-005",ORIGINATIONS!$U:$U,$B16) -> 111217.5 | H16: =SUMIFS(ORIGINATIONS!$L:$L,ORIGINATIONS!$C:$C,"PTR-006",ORIGINATIONS!$U:$U,$B16) -> 75485.25 | I16: =SUM(C16:H16) -> 872060.48
B17: 2022-10 | C17: =SUMIFS(ORIGINATIONS!$L:$L,ORIGINATIONS!$C:$C,"PTR-001",ORIGINATIONS!$U:$U,$B17) -> 61737.04 | D17: =SUMIFS(ORIGINATIONS!$L:$L,ORIGINATIONS!$C:$C,"PTR-002",ORIGINATIONS!$U:$U,$B17) -> 103681.08 | E17: =SUMIFS(ORIGINATIONS!$L:$L,ORIGINATIONS!$C:$C,"PTR-003",ORIGINATIONS!$U:$U,$B17) -> 36498.48 | F17: =SUMIFS(ORIGINATIONS!$L:$L,ORIGINATIONS!$C:$C,"PTR-004",ORIGINATIONS!$U:$U,$B17) -> 153167.22 | G17: =SUMIFS(ORIGINATIONS!$L:$L,ORIGINATIONS!$C:$C,"PTR-005",ORIGINATIONS!$U:$U,$B17) -> 170992.38 | H17: =SUMIFS(ORIGINATIONS!$L:$L,ORIGINATIONS!$C:$C,"PTR-006",ORIGINATIONS!$U:$U,$B17) -> 75202.15 | I17: =SUM(C17:H17) -> 601278.35
B18: 2022-11 | C18: =SUMIFS(ORIGINATIONS!$L:$L,ORIGINATIONS!$C:$C,"PTR-001",ORIGINATIONS!$U:$U,$B18) -> 4616.25 | D18: =SUMIFS(ORIGINATIONS!$L:$L,ORIGINATIONS!$C:$C,"PTR-002",ORIGINATIONS!$U:$U,$B18) -> 332894.73 | E18: =SUMIFS(ORIGINATIONS!$L:$L,ORIGINATIONS!$C:$C,"PTR-003",ORIGINATIONS!$U:$U,$B18) -> 0 | F18: =SUMIFS(ORIGINATIONS!$L:$L,ORIGINATIONS!$C:$C,"PTR-004",ORIGINATIONS!$U:$U,$B18) -> 237845.33 | G18: =SUMIFS(ORIGINATIONS!$L:$L,ORIGINATIONS!$C:$C,"PTR-005",ORIGINATIONS!$U:$U,$B18) -> 170303.91 | H18: =SUMIFS(ORIGINATIONS!$L:$L,ORIGINATIONS!$C:$C,"PTR-006",ORIGINATIONS!$U:$U,$B18) -> 16547.38 | I18: =SUM(C18:H18) -> 762207.6
B19: 2022-12 | C19: =SUMIFS(ORIGINATIONS!$L:$L,ORIGINATIONS!$C:$C,"PTR-001",ORIGINATIONS!$U:$U,$B19) -> 74693 | D19: =SUMIFS(ORIGINATIONS!$L:$L,ORIGINATIONS!$C:$C,"PTR-002",ORIGINATIONS!$U:$U,$B19) -> 37038.87 | E19: =SUMIFS(ORIGINATIONS!$L:$L,ORIGINATIONS!$C:$C,"PTR-003",ORIGINATIONS!$U:$U,$B19) -> 47253.39 | F19: =SUMIFS(ORIGINATIONS!$L:$L,ORIGINATIONS!$C:$C,"PTR-004",ORIGINATIONS!$U:$U,$B19) -> 221972.71 | G19: =SUMIFS(ORIGINATIONS!$L:$L,ORIGINATIONS!$C:$C,"PTR-005",ORIGINATIONS!$U:$U,$B19) -> 30447.41 | H19: =SUMIFS(ORIGINATIONS!$L:$L,ORIGINATIONS!$C:$C,"PTR-006",ORIGINATIONS!$U:$U,$B19) -> 240006.21 | I19: =SUM(C19:H19) -> 651411.59
... B63: 2026-08 | C63: =SUMIFS(ORIGINATIONS!$L:$L,ORIGINATIONS!$C:$C,"PTR-001",ORIGINATIONS!$U:$U,$B63) -> 86329.06 | D63: =SUMIFS(ORIGINATIONS!$L:$L,ORIGINATIONS!$C:$C,"PTR-002",ORIGINATIONS!$U:$U,$B63) -> 66515.47 | E63: =SUMIFS(ORIGINATIONS!$L:$L,ORIGINATIONS!$C:$C,"PTR-003",ORIGINATIONS!$U:$U,$B63) -> 47976.95 | F63: =SUMIFS(ORIGINATIONS!$L:$L,ORIGINATIONS!$C:$C,"PTR-004",ORIGINATIONS!$U:$U,$B63) -> 78219.13 | G63: =SUMIFS(ORIGINATIONS!$L:$L,ORIGINATIONS!$C:$C,"PTR-005",ORIGINATIONS!$U:$U,$B63) -> 0 | H63: =SUMIFS(ORIGINATIONS!$L:$L,ORIGINATIONS!$C:$C,"PTR-006",ORIGINATIONS!$U:$U,$B63) -> 48620.01 | I63: =SUM(C63:H63) -> 327660.62
B64: Grand Total | C64: =SUM(C8:C63) -> 6495171.7 | D64: =SUM(D8:D63) -> 6891240.6 | E64: =SUM(E8:E63) -> 5582528.9 | F64: =SUM(F8:F63) -> 7411529.4 | G64: =SUM(G8:G63) -> 6519837.3 | H64: =SUM(H8:H63) -> 6776667.7 | I64: =SUM(I8:I63) -> 39676976
B87: 3-Month Trailing Average Revenue Run-Rate (Annualized)
B88: Monthly total = SUMIFS on REVENUE_RECOGNIZED!revenue_recognized_usd by recognition_period. Trailing avg = AVERAGE of current month + prior 2 months (blank until 3 months of history exist). Annualized run-rate = trailing 3-mo avg x 12.
B90: Month | C90: Total Revenue Recognized | D90: 3-Mo Trailing Avg | E90: Annualized Run-Rate
B91: 2022-01 | C91: =SUMIFS(REVENUE_RECOGNIZED!$E:$E,REVENUE_RECOGNIZED!$D:$D,$B91) -> 63348.05
B92: 2022-02 | C92: =SUMIFS(REVENUE_RECOGNIZED!$E:$E,REVENUE_RECOGNIZED!$D:$D,$B92) -> 87343
B93: 2022-03 | C93: =SUMIFS(REVENUE_RECOGNIZED!$E:$E,REVENUE_RECOGNIZED!$D:$D,$B93) -> 133630.12 | D93: =AVERAGE(C91:C93) -> 94773.723 | E93: =D93*12 -> 1137284.7
B94: 2022-04 | C94: =SUMIFS(REVENUE_RECOGNIZED!$E:$E,REVENUE_RECOGNIZED!$D:$D,$B94) -> 144921.44 | D94: =AVERAGE(C92:C94) -> 121964.85 | E94: =D94*12 -> 1463578.2
B95: 2022-05 | C95: =SUMIFS(REVENUE_RECOGNIZED!$E:$E,REVENUE_RECOGNIZED!$D:$D,$B95) -> 133872.37 | D95: =AVERAGE(C93:C95) -> 137474.64 | E95: =D95*12 -> 1649695.7
B96: 2022-06 | C96: =SUMIFS(REVENUE_RECOGNIZED!$E:$E,REVENUE_RECOGNIZED!$D:$D,$B96) -> 147141.24 | D96: =AVERAGE(C94:C96) -> 141978.35 | E96: =D96*12 -> 1703740.2
B97: 2022-07 | C97: =SUMIFS(REVENUE_RECOGNIZED!$E:$E,REVENUE_RECOGNIZED!$D:$D,$B97) -> 146299.7 | D97: =AVERAGE(C95:C97) -> 142437.77 | E97: =D97*12 -> 1709253.2
B98: 2022-08 | C98: =SUMIFS(REVENUE_RECOGNIZED!$E:$E,REVENUE_RECOGNIZED!$D:$D,$B98) -> 153204.54 | D98: =AVERAGE(C96:C98) -> 148881.83 | E98: =D98*12 -> 1786581.9
B99: 2022-09 | C99: =SUMIFS(REVENUE_RECOGNIZED!$E:$E,REVENUE_RECOGNIZED!$D:$D,$B99) -> 149916.98 | D99: =AVERAGE(C97:C99) -> 149807.07 | E99: =D99*12 -> 1797684.9
B100: 2022-10 | C100: =SUMIFS(REVENUE_RECOGNIZED!$E:$E,REVENUE_RECOGNIZED!$D:$D,$B100) -> 159618.66 | D100: =AVERAGE(C98:C100) -> 154246.73 | E100: =D100*12 -> 1850960.7
B101: 2022-11 | C101: =SUMIFS(REVENUE_RECOGNIZED!$E:$E,REVENUE_RECOGNIZED!$D:$D,$B101) -> 159680.25 | D101: =AVERAGE(C99:C101) -> 156405.3 | E101: =D101*12 -> 1876863.6
B102: 2022-12 | C102: =SUMIFS(REVENUE_RECOGNIZED!$E:$E,REVENUE_RECOGNIZED!$D:$D,$B102) -> 151932.39 | D102: =AVERAGE(C100:C102) -> 157077.1 | E102: =D102*12 -> 1884925.2
B103: 2023-01 | C103: =SUMIFS(REVENUE_RECOGNIZED!$E:$E,REVENUE_RECOGNIZED!$D:$D,$B103) -> 142505.48 | D103: =AVERAGE(C101:C103) -> 151372.71 | E103: =D103*12 -> 1816472.5
B104: 2023-02 | C104: =SUMIFS(REVENUE_RECOGNIZED!$E:$E,REVENUE_RECOGNIZED!$D:$D,$B104) -> 127937.75 | D104: =AVERAGE(C102:C104) -> 140791.87 | E104: =D104*12 -> 1689502.5
... B146: 2026-08 | C146: =SUMIFS(REVENUE_RECOGNIZED!$E:$E,REVENUE_RECOGNIZED!$D:$D,$B146) -> 13188.76 | D146: =AVERAGE(C144:C146) -> 76362.657 | E146: =D146*12 -> 916351.88
B148: Current Annualized Revenue Run-Rate: | C148: =E146 -> 916351.88

Sheet Reconciliation
B2: Reconciliation — Originations With No Matching Repayments
B3: Anti-join of ORIGINATIONS against REPAYMENTS on origination_id. 'Repayment Count Check' formula should read 0 for every row (confirms the gap dynamically). 'Likely Reason' flags anything funded within the last 14 days as probably just too recent to have a remittance yet; anything older warrants a genuine data-gap review.
B6: origination_id | C6: partner_id | D6: funding_date | E6: advance_amount_usd | F6: status | G6: days_since_funding | H6: repayment_count_check | I6: likely_reason
B7: ORG-300001 | C7: =INDEX(ORIGINATIONS!$C:$C,MATCH($B7,ORIGINATIONS!$A:$A,0)) -> PTR-001 | D7: =INDEX(ORIGINATIONS!$F:$F,MATCH($B7,ORIGINATIONS!$A:$A,0)) -> 46241 | E7: =INDEX(ORIGINATIONS!$L:$L,MATCH($B7,ORIGINATIONS!$A:$A,0)) -> 76089.9 | F7: =INDEX(ORIGINATIONS!$R:$R,MATCH($B7,ORIGINATIONS!$A:$A,0)) -> active | G7: =TODAY()-$D7 -> 7 | H7: =COUNTIFS(REPAYMENTS!$B:$B,$B7) -> 0 | I7: =IF($G7<14,"Likely too recent (<14 days) - not a gap","Review - potential data gap") -> Likely too recent (<14 days) - not a gap
B8: ORG-300002 | C8: =INDEX(ORIGINATIONS!$C:$C,MATCH($B8,ORIGINATIONS!$A:$A,0)) -> PTR-001 | D8: =INDEX(ORIGINATIONS!$F:$F,MATCH($B8,ORIGINATIONS!$A:$A,0)) -> 46240 | E8: =INDEX(ORIGINATIONS!$L:$L,MATCH($B8,ORIGINATIONS!$A:$A,0)) -> 10239.16 | F8: =INDEX(ORIGINATIONS!$R:$R,MATCH($B8,ORIGINATIONS!$A:$A,0)) -> active | G8: =TODAY()-$D8 -> 8 | H8: =COUNTIFS(REPAYMENTS!$B:$B,$B8) -> 0 | I8: =IF($G8<14,"Likely too recent (<14 days) - not a gap","Review - potential data gap") -> Likely too recent (<14 days) - not a gap
B9: ORG-300003 | C9: =INDEX(ORIGINATIONS!$C:$C,MATCH($B9,ORIGINATIONS!$A:$A,0)) -> PTR-004 | D9: =INDEX(ORIGINATIONS!$F:$F,MATCH($B9,ORIGINATIONS!$A:$A,0)) -> 46246 | E9: =INDEX(ORIGINATIONS!$L:$L,MATCH($B9,ORIGINATIONS!$A:$A,0)) -> 78219.13 | F9: =INDEX(ORIGINATIONS!$R:$R,MATCH($B9,ORIGINATIONS!$A:$A,0)) -> active | G9: =TODAY()-$D9 -> 2 | H9: =COUNTIFS(REPAYMENTS!$B:$B,$B9) -> 0 | I9: =IF($G9<14,"Likely too recent (<14 days) - not a gap","Review - potential data gap") -> Likely too recent (<14 days) - not a gap
B10: ORG-300004 | C10: =INDEX(ORIGINATIONS!$C:$C,MATCH($B10,ORIGINATIONS!$A:$A,0)) -> PTR-006 | D10: =INDEX(ORIGINATIONS!$F:$F,MATCH($B10,ORIGINATIONS!$A:$A,0)) -> 46245 | E10: =INDEX(ORIGINATIONS!$L:$L,MATCH($B10,ORIGINATIONS!$A:$A,0)) -> 48620.01 | F10: =INDEX(ORIGINATIONS!$R:$R,MATCH($B10,ORIGINATIONS!$A:$A,0)) -> active | G10: =TODAY()-$D10 -> 3 | H10: =COUNTIFS(REPAYMENTS!$B:$B,$B10) -> 0 | I10: =IF($G10<14,"Likely too recent (<14 days) - not a gap","Review - potential data gap") -> Likely too recent (<14 days) - not a gap
B11: ORG-300005 | C11: =INDEX(ORIGINATIONS!$C:$C,MATCH($B11,ORIGINATIONS!$A:$A,0)) -> PTR-002 | D11: =INDEX(ORIGINATIONS!$F:$F,MATCH($B11,ORIGINATIONS!$A:$A,0)) -> 46241 | E11: =INDEX(ORIGINATIONS!$L:$L,MATCH($B11,ORIGINATIONS!$A:$A,0)) -> 39920.14 | F11: =INDEX(ORIGINATIONS!$R:$R,MATCH($B11,ORIGINATIONS!$A:$A,0)) -> active | G11: =TODAY()-$D11 -> 7 | H11: =COUNTIFS(REPAYMENTS!$B:$B,$B11) -> 0 | I11: =IF($G11<14,"Likely too recent (<14 days) - not a gap","Review - potential data gap") -> Likely too recent (<14 days) - not a gap
B12: ORG-300006 | C12: =INDEX(ORIGINATIONS!$C:$C,MATCH($B12,ORIGINATIONS!$A:$A,0)) -> PTR-002 | D12: =INDEX(ORIGINATIONS!$F:$F,MATCH($B12,ORIGINATIONS!$A:$A,0)) -> 46239 | E12: =INDEX(ORIGINATIONS!$L:$L,MATCH($B12,ORIGINATIONS!$A:$A,0)) -> 26595.33 | F12: =INDEX(ORIGINATIONS!$R:$R,MATCH($B12,ORIGINATIONS!$A:$A,0)) -> active | G12: =TODAY()-$D12 -> 9 | H12: =COUNTIFS(REPAYMENTS!$B:$B,$B12) -> 0 | I12: =IF($G12<14,"Likely too recent (<14 days) - not a gap","Review - potential data gap") -> Likely too recent (<14 days) - not a gap
B13: ORG-300007 | C13: =INDEX(ORIGINATIONS!$C:$C,MATCH($B13,ORIGINATIONS!$A:$A,0)) -> PTR-003 | D13: =INDEX(ORIGINATIONS!$F:$F,MATCH($B13,ORIGINATIONS!$A:$A,0)) -> 46238 | E13: =INDEX(ORIGINATIONS!$L:$L,MATCH($B13,ORIGINATIONS!$A:$A,0)) -> 47976.95 | F13: =INDEX(ORIGINATIONS!$R:$R,MATCH($B13,ORIGINATIONS!$A:$A,0)) -> active | G13: =TODAY()-$D13 -> 10 | H13: =COUNTIFS(REPAYMENTS!$B:$B,$B13) -> 0 | I13: =IF($G13<14,"Likely too recent (<14 days) - not a gap","Review - potential data gap") -> Likely too recent (<14 days) - not a gap
B14: ORG-300008 | C14: =INDEX(ORIGINATIONS!$C:$C,MATCH($B14,ORIGINATIONS!$A:$A,0)) -> PTR-003 | D14: =INDEX(ORIGINATIONS!$F:$F,MATCH($B14,ORIGINATIONS!$A:$A,0)) -> 45978 | E14: =INDEX(ORIGINATIONS!$L:$L,MATCH($B14,ORIGINATIONS!$A:$A,0)) -> 33704.92 | F14: =INDEX(ORIGINATIONS!$R:$R,MATCH($B14,ORIGINATIONS!$A:$A,0)) -> active | G14: =TODAY()-$D14 -> 270 | H14: =COUNTIFS(REPAYMENTS!$B:$B,$B14) -> 0 | I14: =IF($G14<14,"Likely too recent (<14 days) - not a gap","Review - potential data gap") -> Review - potential data gap
B15: ORG-300009 | C15: =INDEX(ORIGINATIONS!$C:$C,MATCH($B15,ORIGINATIONS!$A:$A,0)) -> PTR-001 | D15: =INDEX(ORIGINATIONS!$F:$F,MATCH($B15,ORIGINATIONS!$A:$A,0)) -> 45876 | E15: =INDEX(ORIGINATIONS!$L:$L,MATCH($B15,ORIGINATIONS!$A:$A,0)) -> 27350.26 | F15: =INDEX(ORIGINATIONS!$R:$R,MATCH($B15,ORIGINATIONS!$A:$A,0)) -> active | G15: =TODAY()-$D15 -> 372 | H15: =COUNTIFS(REPAYMENTS!$B:$B,$B15) -> 0 | I15: =IF($G15<14,"Likely too recent (<14 days) - not a gap","Review - potential data gap") -> Review - potential data gap
B16: ORG-300010 | C16: =INDEX(ORIGINATIONS!$C:$C,MATCH($B16,ORIGINATIONS!$A:$A,0)) -> PTR-004 | D16: =INDEX(ORIGINATIONS!$F:$F,MATCH($B16,ORIGINATIONS!$A:$A,0)) -> 45946 | E16: =INDEX(ORIGINATIONS!$L:$L,MATCH($B16,ORIGINATIONS!$A:$A,0)) -> 29547.49 | F16: =INDEX(ORIGINATIONS!$R:$R,MATCH($B16,ORIGINATIONS!$A:$A,0)) -> active | G16: =TODAY()-$D16 -> 302 | H16: =COUNTIFS(REPAYMENTS!$B:$B,$B16) -> 0 | I16: =IF($G16<14,"Likely too recent (<14 days) - not a gap","Review - potential data gap") -> Review - potential data gap
B20: Summary
B21: Total originations with no repayments: | D21: 10
B22: ...of which likely just too recent (<14 days): | D22: =COUNTIF(I7:I16,"Likely too recent (<14 days) - not a gap") -> 7
B23: ...of which need genuine data-gap review: | D23: =COUNTIF(I7:I16,"Review - potential data gap") -> 3

Sheet Cohort Delinquency
B2: Cohort Delinquency — % of Cohort Dollar Volume Currently Delinquent or Defaulted
B3: Cohort = origination (funding) month. Delinquent/Default Volume = SUMIFS of advance_amount_usd where status is 'delinquent' or 'default', by cohort. % = Delinquent/Default Volume ÷ Total Cohort Volume.
B6: Cohort Month | C6: Total Origination Volume | D6: Delinquent + Default Volume | E6: % Delinquent/Default | F6: Originations Count
B7: 2022-01 | C7: =SUMIFS(ORIGINATIONS!$L:$L,ORIGINATIONS!$U:$U,$B7) -> 1017432.7 | D7: =SUMIFS(ORIGINATIONS!$L:$L,ORIGINATIONS!$U:$U,$B7,ORIGINATIONS!$R:$R,"delinquent")+SUMIFS(ORIGINATIONS!$L:$L,ORIGINATIONS!$U:$U,$B7,ORIGINATIONS!$R:$R,"default") -> 102852.15 | E7: =IFERROR(D7/C7,0) -> 0.10108989 | F7: =COUNTIFS(ORIGINATIONS!$U:$U,$B7) -> 31
B8: 2022-02 | C8: =SUMIFS(ORIGINATIONS!$L:$L,ORIGINATIONS!$U:$U,$B8) -> 531860.35 | D8: =SUMIFS(ORIGINATIONS!$L:$L,ORIGINATIONS!$U:$U,$B8,ORIGINATIONS!$R:$R,"delinquent")+SUMIFS(ORIGINATIONS!$L:$L,ORIGINATIONS!$U:$U,$B8,ORIGINATIONS!$R:$R,"default") -> 132214.97 | E8: =IFERROR(D8/C8,0) -> 0.24858963 | F8: =COUNTIFS(ORIGINATIONS!$U:$U,$B8) -> 20
B9: 2022-03 | C9: =SUMIFS(ORIGINATIONS!$L:$L,ORIGINATIONS!$U:$U,$B9) -> 744198.28 | D9: =SUMIFS(ORIGINATIONS!$L:$L,ORIGINATIONS!$U:$U,$B9,ORIGINATIONS!$R:$R,"delinquent")+SUMIFS(ORIGINATIONS!$L:$L,ORIGINATIONS!$U:$U,$B9,ORIGINATIONS!$R:$R,"default") -> 63293.71 | E9: =IFERROR(D9/C9,0) -> 0.085049525 | F9: =COUNTIFS(ORIGINATIONS!$U:$U,$B9) -> 24
B10: 2022-04 | C10: =SUMIFS(ORIGINATIONS!$L:$L,ORIGINATIONS!$U:$U,$B10) -> 1013685.4 | D10: =SUMIFS(ORIGINATIONS!$L:$L,ORIGINATIONS!$U:$U,$B10,ORIGINATIONS!$R:$R,"delinquent")+SUMIFS(ORIGINATIONS!$L:$L,ORIGINATIONS!$U:$U,$B10,ORIGINATIONS!$R:$R,"default") -> 133870.49 | E10: =IFERROR(D10/C10,0) -> 0.13206315 | F10: =COUNTIFS(ORIGINATIONS!$U:$U,$B10) -> 27
B11: 2022-05 | C11: =SUMIFS(ORIGINATIONS!$L:$L,ORIGINATIONS!$U:$U,$B11) -> 649055.93 | D11: =SUMIFS(ORIGINATIONS!$L:$L,ORIGINATIONS!$U:$U,$B11,ORIGINATIONS!$R:$R,"delinquent")+SUMIFS(ORIGINATIONS!$L:$L,ORIGINATIONS!$U:$U,$B11,ORIGINATIONS!$R:$R,"default") -> 7744.66 | E11: =IFERROR(D11/C11,0) -> 0.011932192 | F11: =COUNTIFS(ORIGINATIONS!$U:$U,$B11) -> 17
B12: 2022-06 | C12: =SUMIFS(ORIGINATIONS!$L:$L,ORIGINATIONS!$U:$U,$B12) -> 910333.4 | D12: =SUMIFS(ORIGINATIONS!$L:$L,ORIGINATIONS!$U:$U,$B12,ORIGINATIONS!$R:$R,"delinquent")+SUMIFS(ORIGINATIONS!$L:$L,ORIGINATIONS!$U:$U,$B12,ORIGINATIONS!$R:$R,"default") -> 0 | E12: =IFERROR(D12/C12,0) -> 0 | F12: =COUNTIFS(ORIGINATIONS!$U:$U,$B12) -> 23
B13: 2022-07 | C13: =SUMIFS(ORIGINATIONS!$L:$L,ORIGINATIONS!$U:$U,$B13) -> 769985.79 | D13: =SUMIFS(ORIGINATIONS!$L:$L,ORIGINATIONS!$U:$U,$B13,ORIGINATIONS!$R:$R,"delinquent")+SUMIFS(ORIGINATIONS!$L:$L,ORIGINATIONS!$U:$U,$B13,ORIGINATIONS!$R:$R,"default") -> 70701.91 | E13: =IFERROR(D13/C13,0) -> 0.091822357 | F13: =COUNTIFS(ORIGINATIONS!$U:$U,$B13) -> 23
B14: 2022-08 | C14: =SUMIFS(ORIGINATIONS!$L:$L,ORIGINATIONS!$U:$U,$B14) -> 641094.81 | D14: =SUMIFS(ORIGINATIONS!$L:$L,ORIGINATIONS!$U:$U,$B14,ORIGINATIONS!$R:$R,"delinquent")+SUMIFS(ORIGINATIONS!$L:$L,ORIGINATIONS!$U:$U,$B14,ORIGINATIONS!$R:$R,"default") -> 0 | E14: =IFERROR(D14/C14,0) -> 0 | F14: =COUNTIFS(ORIGINATIONS!$U:$U,$B14) -> 22
B15: 2022-09 | C15: =SUMIFS(ORIGINATIONS!$L:$L,ORIGINATIONS!$U:$U,$B15) -> 872060.48 | D15: =SUMIFS(ORIGINATIONS!$L:$L,ORIGINATIONS!$U:$U,$B15,ORIGINATIONS!$R:$R,"delinquent")+SUMIFS(ORIGINATIONS!$L:$L,ORIGINATIONS!$U:$U,$B15,ORIGINATIONS!$R:$R,"default") -> 76298.85 | E15: =IFERROR(D15/C15,0) -> 0.087492613 | F15: =COUNTIFS(ORIGINATIONS!$U:$U,$B15) -> 30
B16: 2022-10 | C16: =SUMIFS(ORIGINATIONS!$L:$L,ORIGINATIONS!$U:$U,$B16) -> 601278.35 | D16: =SUMIFS(ORIGINATIONS!$L:$L,ORIGINATIONS!$U:$U,$B16,ORIGINATIONS!$R:$R,"delinquent")+SUMIFS(ORIGINATIONS!$L:$L,ORIGINATIONS!$U:$U,$B16,ORIGINATIONS!$R:$R,"default") -> 0 | E16: =IFERROR(D16/C16,0) -> 0 | F16: =COUNTIFS(ORIGINATIONS!$U:$U,$B16) -> 21
B17: 2022-11 | C17: =SUMIFS(ORIGINATIONS!$L:$L,ORIGINATIONS!$U:$U,$B17) -> 762207.6 | D17: =SUMIFS(ORIGINATIONS!$L:$L,ORIGINATIONS!$U:$U,$B17,ORIGINATIONS!$R:$R,"delinquent")+SUMIFS(ORIGINATIONS!$L:$L,ORIGINATIONS!$U:$U,$B17,ORIGINATIONS!$R:$R,"default") -> 55321.61 | E17: =IFERROR(D17/C17,0) -> 0.072580764 | F17: =COUNTIFS(ORIGINATIONS!$U:$U,$B17) -> 23
B18: 2022-12 | C18: =SUMIFS(ORIGINATIONS!$L:$L,ORIGINATIONS!$U:$U,$B18) -> 651411.59 | D18: =SUMIFS(ORIGINATIONS!$L:$L,ORIGINATIONS!$U:$U,$B18,ORIGINATIONS!$R:$R,"delinquent")+SUMIFS(ORIGINATIONS!$L:$L,ORIGINATIONS!$U:$U,$B18,ORIGINATIONS!$R:$R,"default") -> 13766.44 | E18: =IFERROR(D18/C18,0) -> 0.021133244 | F18: =COUNTIFS(ORIGINATIONS!$U:$U,$B18) -> 18
... B62: 2026-08 | C62: =SUMIFS(ORIGINATIONS!$L:$L,ORIGINATIONS!$U:$U,$B62) -> 327660.62 | D62: =SUMIFS(ORIGINATIONS!$L:$L,ORIGINATIONS!$U:$U,$B62,ORIGINATIONS!$R:$R,"delinquent")+SUMIFS(ORIGINATIONS!$L:$L,ORIGINATIONS!$U:$U,$B62,ORIGINATIONS!$R:$R,"default") -> 0 | E62: =IFERROR(D62/C62,0) -> 0 | F62: =COUNTIFS(ORIGINATIONS!$U:$U,$B62) -> 7
B63: All Cohorts | C63: =SUM(C7:C62) -> 39676976 | D63: =SUM(D7:D62) -> 2771812.7 | E63: =IFERROR(D63/C63,0) -> 0.069859476 | F63: =SUM(F7:F62) -> 1210

Sheet PARTNERS
A1: partner_id | B1: partner_name | C1: partner_category | D1: integration_type | E1: partner_since_date | F1: platform_revenue_share_pct | G1: primary_verticals_served
A2: PTR-001 | B2: DoorDash | C2: Food & Delivery | D2: API - Embedded Checkout | E2: 44270 | F2: 0.015 | G2: Restaurant, Ghost Kitchen, Cafe, Bakery
A3: PTR-002 | B3: Amazon | C3: E-commerce Marketplace | D3: API - Seller Central Widget | E3: 44136 | F3: 0.012 | G3: E-commerce Retail, CPG Brand, Marketplace Reseller
A4: PTR-003 | B4: Worldpay | C4: Payments / Acquiring | D4: White-label Embedded | E4: 44571 | F4: 0.018 | G4: Retail Store, Auto Repair, Salon, Convenience Store
A5: PTR-004 | B5: Mindbody | C5: Wellness SaaS | D5: API - Embedded Dashboard | E5: 44430 | F5: 0.02 | G5: Fitness Studio, Spa, Yoga Studio, Wellness Clinic
A6: PTR-005 | B6: Toast | C6: Restaurant POS | D6: API - Embedded Checkout | E6: 44717 | F6: 0.016 | G6: Restaurant, Bar, Food Truck
A7: PTR-006 | B7: Squarespace | C7: E-commerce / Website Builder | D7: White-label Embedded | E7: 44971 | F7: 0.014 | G7: E-commerce Retail, Creative Services, Photography Studio

Sheet ORIGINATIONS
A1: origination_id | B1: merchant_id | C1: partner_id | D1: business_vertical | E1: state | F1: funding_date | G1: estimated_maturity_date | H1: avg_monthly_gmv_usd | I1: prior_advances_count | J1: risk_score | K1: industry_risk_tier | L1: advance_amount_usd | M1: factor_rate | N1: total_repayment_usd | O1: total_fee_usd | P1: remittance_rate | Q1: term_estimate_days | R1: status | S1: pct_repaid | T1: amount_repaid_usd | U1: funding_month
A2: ORG-200001 | B2: MCH-100001 | C2: PTR-006 | D2: E-commerce Retail | E2: CA | F2: 44623 | G2: 44740 | H2: 187455.22 | I2: 0 | J2: 545 | K2: low | L2: 70152.4 | M2: 1.103 | N2: 77378.1 | O2: 7225.7 | P2: 0.105 | Q2: 117 | R2: active | S2: 0.781 | T2: 60432.3 | U2: 2022-03
A3: ORG-200002 | B3: MCH-100002 | C3: PTR-003 | D3: Retail Store | E3: NC | F3: 45961 | G3: 46021 | H3: 217689.05 | I3: 1 | J3: 645 | K3: medium | L3: 28288.7 | M3: 1.261 | N3: 35672.05 | O3: 7383.35 | P3: 0.141 | Q3: 60 | R3: completed | S3: 1 | T3: 35672.05 | U3: 2025-10
A4: ORG-200003 | B4: MCH-100003 | C4: PTR-001 | D4: Cafe | E4: MA | F4: 44854 | G4: 44914 | H4: 72793.29 | I4: 0 | J4: 802 | K4: medium | L4: 11497.45 | M4: 1.319 | N4: 15165.14 | O4: 3667.69 | P4: 0.134 | Q4: 60 | R4: active | S4: 0.786 | T4: 11919.8 | U4: 2022-10
A5: ORG-200004 | B5: MCH-100004 | C5: PTR-004 | D5: Wellness Clinic | E5: OR | F5: 44790 | G5: 44870 | H5: 68842.22 | I5: 1 | J5: 802 | K5: low | L5: 21375.84 | M5: 1.152 | N5: 24624.97 | O5: 3249.13 | P5: 0.133 | Q5: 80 | R5: completed | S5: 1 | T5: 24624.97 | U5: 2022-08
A6: ORG-200005 | B6: MCH-100005 | C6: PTR-005 | D6: Restaurant | E6: MN | F6: 46060 | G6: 46146 | H6: 86445.77 | I6: 0 | J6: 797 | K6: medium | L6: 12112.05 | M6: 1.233 | N6: 14934.16 | O6: 2822.11 | P6: 0.06 | Q6: 86 | R6: completed | S6: 1 | T6: 14934.16 | U6: 2026-02
A7: ORG-200006 | B7: MCH-100006 | C7: PTR-006 | D7: Photography Studio | E7: CO | F7: 44576 | G7: 44636 | H7: 114020.22 | I7: 1 | J7: 539 | K7: medium | L7: 9037.48 | M7: 1.23 | N7: 11116.1 | O7: 2078.62 | P7: 0.126 | Q7: 60 | R7: active | S7: 0.921 | T7: 10237.93 | U7: 2022-01
A8: ORG-200007 | B8: MCH-100007 | C8: PTR-004 | D8: Yoga Studio | E8: NJ | F8: 44954 | G8: 45030 | H8: 107486.75 | I8: 3 | J8: 517 | K8: low | L8: 13566.39 | M8: 1.296 | N8: 17582.04 | O8: 4015.65 | P8: 0.064 | Q8: 76 | R8: active | S8: 0.857 | T8: 15067.81 | U8: 2023-01
A9: ORG-200008 | B9: MCH-100008 | C9: PTR-004 | D9: Yoga Studio | E9: TN | F9: 45672 | G9: 45732 | H9: 77030.31 | I9: 2 | J9: 734 | K9: high | L9: 9454.12 | M9: 1.342 | N9: 12687.43 | O9: 3233.31 | P9: 0.125 | Q9: 60 | R9: active | S9: 0.81 | T9: 10276.82 | U9: 2025-01
A10: ORG-200009 | B10: MCH-100009 | C10: PTR-001 | D10: Bakery | E10: MD | F10: 45209 | G10: 45275 | H10: 144784.92 | I10: 0 | J10: 583 | K10: medium | L10: 22524.87 | M10: 1.261 | N10: 28403.86 | O10: 5878.99 | P10: 0.089 | Q10: 66 | R10: active | S10: 0.98 | T10: 27835.78 | U10: 2023-10
A11: ORG-200010 | B11: MCH-100010 | C11: PTR-006 | D11: Photography Studio | E11: PA | F11: 45800 | G11: 45860 | H11: 233484.96 | I11: 0 | J11: 781 | K11: medium | L11: 22709.15 | M11: 1.229 | N11: 27909.55 | O11: 5200.4 | P11: 0.085 | Q11: 60 | R11: active | S11: 0.82 | T11: 22885.83 | U11: 2025-05
A12: ORG-200011 | B12: MCH-100011 | C12: PTR-005 | D12: Restaurant | E12: FL | F12: 45193 | G12: 45377 | H12: 26209.01 | I12: 3 | J12: 789 | K12: low | L12: 9665.29 | M12: 1.12 | N12: 10825.12 | O12: 1159.83 | P12: 0.067 | Q12: 184 | R12: completed | S12: 1 | T12: 10825.12 | U12: 2023-09
A13: ORG-200012 | B13: MCH-100012 | C13: PTR-001 | D13: Restaurant | E13: MN | F13: 44565 | G13: 44625 | H13: 113164.43 | I13: 2 | J13: 600 | K13: low | L13: 25062.29 | M13: 1.149 | N13: 28796.57 | O13: 3734.28 | P13: 0.142 | Q13: 60 | R13: completed | S13: 1 | T13: 28796.57 | U13: 2022-01
... A1211: ORG-300010 | B1211: MCH-400010 | C1211: PTR-004 | D1211: Bar | E1211: NY | F1211: 45946 | G1211: 46180 | H1211: 107755.3 | I1211: 1 | J1211: 750 | K1211: medium | L1211: 29547.49 | M1211: 1.274 | N1211: 37643.5 | O1211: 8096.01 | P1211: 0.067 | Q1211: 234 | R1211: active | S1211: 0 | T1211: 0 | U1211: 2025-10

Sheet REPAYMENTS
A1: repayment_id | B1: origination_id | C1: partner_id | D1: payment_date | E1: remittance_amount_usd | F1: cumulative_repaid_usd | G1: payment_method
A2: RPY-0000001 | B2: ORG-200001 | C2: PTR-006 | D2: 44630 | E2: 4085.28 | F2: 4085.28 | G2: ach_remittance
A3: RPY-0000002 | B3: ORG-200001 | C3: PTR-006 | D3: 44637 | E3: 4429.75 | F3: 8515.03 | G3: ach_remittance
A4: RPY-0000003 | B4: ORG-200001 | C4: PTR-006 | D4: 44644 | E4: 3533.84 | F4: 12048.87 | G4: ach_remittance
A5: RPY-0000004 | B5: ORG-200001 | C5: PTR-006 | D5: 44651 | E5: 3106.8 | F5: 15155.67 | G5: ach_remittance
A6: RPY-0000005 | B6: ORG-200001 | C6: PTR-006 | D6: 44658 | E6: 4559.03 | F6: 19714.7 | G6: ach_remittance
A7: RPY-0000006 | B7: ORG-200001 | C7: PTR-006 | D7: 44665 | E7: 3543.19 | F7: 23257.89 | G7: ach_remittance
A8: RPY-0000007 | B8: ORG-200001 | C8: PTR-006 | D8: 44672 | E8: 2916.81 | F8: 26174.7 | G8: ach_remittance
A9: RPY-0000008 | B9: ORG-200001 | C9: PTR-006 | D9: 44679 | E9: 2575.05 | F9: 28749.75 | G9: ach_remittance
A10: RPY-0000009 | B10: ORG-200001 | C10: PTR-006 | D10: 44686 | E10: 3350.91 | F10: 32100.66 | G10: ach_remittance
A11: RPY-0000010 | B11: ORG-200001 | C11: PTR-006 | D11: 44693 | E11: 3065.49 | F11: 35166.15 | G11: manual_payment
A12: RPY-0000011 | B12: ORG-200001 | C12: PTR-006 | D12: 44700 | E12: 3654.42 | F12: 38820.57 | G12: ach_remittance
A13: RPY-0000012 | B13: ORG-200001 | C13: PTR-006 | D13: 44707 | E13: 5053.03 | F13: 43873.6 | G13: manual_payment
... A12995: RPY-0012994 | B12995: ORG-201200 | C12995: PTR-003 | D12995: 45403 | E12995: 3429.12 | F12995: 27436.51 | G12995: ach_remittance

Sheet REVENUE_RECOGNIZED
A1: revenue_id | B1: origination_id | C1: partner_id | D1: recognition_period | E1: revenue_recognized_usd | F1: cumulative_revenue_recognized_usd | G1: recognition_method
A2: REV-0000001 | B2: ORG-200001 | C2: PTR-006 | D2: 2022-03 | E2: 1806.42 | F2: 1806.42 | G2: straight_line_fee_recognition
A3: REV-0000002 | B3: ORG-200001 | C3: PTR-006 | D3: 2022-04 | E3: 1806.42 | F3: 3612.84 | G3: straight_line_fee_recognition
A4: REV-0000003 | B4: ORG-200001 | C4: PTR-006 | D4: 2022-05 | E4: 1806.42 | F4: 5419.26 | G4: straight_line_fee_recognition
A5: REV-0000004 | B5: ORG-200001 | C5: PTR-006 | D5: 2022-06 | E5: 1806.42 | F5: 7225.68 | G5: straight_line_fee_recognition
A6: REV-0000005 | B6: ORG-200002 | C6: PTR-003 | D6: 2025-10 | E6: 3691.68 | F6: 3691.68 | G6: straight_line_fee_recognition
A7: REV-0000006 | B7: ORG-200002 | C7: PTR-003 | D7: 2025-11 | E7: 3691.68 | F7: 7383.36 | G7: straight_line_fee_recognition
A8: REV-0000007 | B8: ORG-200003 | C8: PTR-001 | D8: 2022-10 | E8: 1833.85 | F8: 1833.85 | G8: straight_line_fee_recognition
A9: REV-0000008 | B9: ORG-200003 | C9: PTR-001 | D9: 2022-11 | E9: 1833.85 | F9: 3667.7 | G9: straight_line_fee_recognition
A10: REV-0000009 | B10: ORG-200004 | C10: PTR-004 | D10: 2022-08 | E10: 1083.04 | F10: 1083.04 | G10: straight_line_fee_recognition
A11: REV-0000010 | B11: ORG-200004 | C11: PTR-004 | D11: 2022-09 | E11: 1083.04 | F11: 2166.08 | G11: straight_line_fee_recognition
A12: REV-0000011 | B12: ORG-200004 | C12: PTR-004 | D12: 2022-10 | E12: 1083.04 | F12: 3249.12 | G12: straight_line_fee_recognition
A13: REV-0000012 | B13: ORG-200005 | C13: PTR-005 | D13: 2026-02 | E13: 940.7 | F13: 940.7 | G13: straight_line_fee_recognition
... A4017: REV-0004016 | B4017: ORG-201200 | C4017: PTR-003 | D4017: 2024-03 | E4017: 1805.79 | F4017: 3611.58 | G4017: straight_line_fee_recognition
